DNA_analyser_IBP/__init__.py
DNA_analyser_IBP/adapters/__init__.py
DNA_analyser_IBP/adapters/base_adapter.py
DNA_analyser_IBP/adapters/batch_adapter.py
DNA_analyser_IBP/adapters/cpg_adapter.py
DNA_analyser_IBP/adapters/g4hunter_adapter.py
DNA_analyser_IBP/adapters/g4killer_adapter.py
DNA_analyser_IBP/adapters/p53_adapter.py
DNA_analyser_IBP/adapters/rloopr_adapter.py
DNA_analyser_IBP/adapters/sequence_adapter.py
DNA_analyser_IBP/adapters/user_adapter.py
DNA_analyser_IBP/adapters/validations.py
DNA_analyser_IBP/adapters/zdna_adapter.py
DNA_analyser_IBP/api.py
DNA_analyser_IBP/batch_statuses.py
DNA_analyser_IBP/config.py
DNA_analyser_IBP/interfaces/__init__.py
DNA_analyser_IBP/interfaces/analyse_interface.py
DNA_analyser_IBP/interfaces/cpg_interface.py
DNA_analyser_IBP/interfaces/extras_interface.py
DNA_analyser_IBP/interfaces/g4hunter_interface.py
DNA_analyser_IBP/interfaces/g4killer_interface.py
DNA_analyser_IBP/interfaces/p53_interface.py
DNA_analyser_IBP/interfaces/rloopr_interface.py
DNA_analyser_IBP/interfaces/sequence_interface.py
DNA_analyser_IBP/interfaces/tool_interface.py
DNA_analyser_IBP/interfaces/zdna_interface.py
DNA_analyser_IBP/intersection/__init__.py
DNA_analyser_IBP/intersection/annotation.py
DNA_analyser_IBP/intersection/g4_result.py
DNA_analyser_IBP/models/__init__.py
DNA_analyser_IBP/models/analyse.py
DNA_analyser_IBP/models/base.py
DNA_analyser_IBP/models/batch.py
DNA_analyser_IBP/models/cpg.py
DNA_analyser_IBP/models/g4hunter.py
DNA_analyser_IBP/models/g4killer.py
DNA_analyser_IBP/models/p53.py
DNA_analyser_IBP/models/rloopr.py
DNA_analyser_IBP/models/sequence.py
DNA_analyser_IBP/models/user.py
DNA_analyser_IBP/models/zdna.py
DNA_analyser_IBP/ports/__init__.py
DNA_analyser_IBP/ports/batch_port.py
DNA_analyser_IBP/ports/cpg_port.py
DNA_analyser_IBP/ports/g4hunter_port.py
DNA_analyser_IBP/ports/g4killer_port.py
DNA_analyser_IBP/ports/p53_port.py
DNA_analyser_IBP/ports/port.py
DNA_analyser_IBP/ports/rloopr_port.py
dna_analyser_ibp-3.7.1.dist-info/LICENSE
dna_analyser_ibp-3.7.1.dist-info/METADATA
dna_analyser_ibp-3.7.1.dist-info/WHEEL
dna_analyser_ibp-3.7.1.dist-info/RECORD
