Metadata-Version: 2.3
Name: DNA_analyser_IBP
Version: 3.7.1
Summary: DNA analyser API wrapper tool for Jupiter notebooks.
License: GPL-3.0-or-later
Keywords: DNA,g4hunter,g4killer,p53
Author: Patrik Kaura
Author-email: patrikkaura@gmail.com
Requires-Python: >=3.10,<4.0
Classifier: Intended Audience :: Education
Classifier: Intended Audience :: Science/Research
Classifier: License :: OSI Approved :: GNU General Public License v3 (GPLv3)
Classifier: License :: OSI Approved :: GNU General Public License v3 or later (GPLv3+)
Classifier: Operating System :: OS Independent
Classifier: Programming Language :: Python
Classifier: Programming Language :: Python :: 3
Classifier: Programming Language :: Python :: 3.10
Classifier: Programming Language :: Python :: 3.11
Classifier: Programming Language :: Python :: 3.12
Classifier: Programming Language :: Python :: 3.13
Classifier: Programming Language :: Python :: 3.6
Classifier: Programming Language :: Python :: 3.7
Classifier: Programming Language :: Python :: 3.8
Classifier: Topic :: Scientific/Engineering :: Bio-Informatics
Requires-Dist: matplotlib (==3.10.1)
Requires-Dist: pandas (==2.2.3)
Requires-Dist: pyjwt (==2.8.0)
Requires-Dist: pytest (==7.4.2)
Requires-Dist: requests (==2.32.3)
Requires-Dist: requests-toolbelt (==1.0.0)
Requires-Dist: tenacity (==8.2.3)
Requires-Dist: tqdm (==4.66.0)
Project-URL: Documentation, https://github.com/patrikkaura/dna-analyser-ibp/
Project-URL: Homepage, http://bioinformatics.ibp.cz/
Project-URL: Repository, https://github.com/patrikkaura/dna-analyser-ibp
